odoo/addons/stock_picking_report_qty_undelivered/README.rst
odoo/addons/stock_picking_report_qty_undelivered/__init__.py
odoo/addons/stock_picking_report_qty_undelivered/__manifest__.py
odoo/addons/stock_picking_report_qty_undelivered/i18n/es.po
odoo/addons/stock_picking_report_qty_undelivered/i18n/it.po
odoo/addons/stock_picking_report_qty_undelivered/i18n/stock_picking_report_qty_undelivered.pot
odoo/addons/stock_picking_report_qty_undelivered/models/__init__.py
odoo/addons/stock_picking_report_qty_undelivered/models/stock_picking_type.py
odoo/addons/stock_picking_report_qty_undelivered/readme/CONFIGURE.md
odoo/addons/stock_picking_report_qty_undelivered/readme/CONTEXT.md
odoo/addons/stock_picking_report_qty_undelivered/readme/CONTRIBUTORS.md
odoo/addons/stock_picking_report_qty_undelivered/readme/DESCRIPTION.md
odoo/addons/stock_picking_report_qty_undelivered/readme/USAGE.md
odoo/addons/stock_picking_report_qty_undelivered/static/description/icon.png
odoo/addons/stock_picking_report_qty_undelivered/static/description/index.html
odoo/addons/stock_picking_report_qty_undelivered/tests/__init__.py
odoo/addons/stock_picking_report_qty_undelivered/tests/test_stock_picking_report_qty_undelivered.py
odoo/addons/stock_picking_report_qty_undelivered/views/report_deliveryslip.xml
odoo/addons/stock_picking_report_qty_undelivered/views/stock_picking_type_views.xml
odoo_addon_stock_picking_report_qty_undelivered-16.0.1.0.1.3.dist-info/METADATA
odoo_addon_stock_picking_report_qty_undelivered-16.0.1.0.1.3.dist-info/WHEEL
odoo_addon_stock_picking_report_qty_undelivered-16.0.1.0.1.3.dist-info/top_level.txt
odoo_addon_stock_picking_report_qty_undelivered-16.0.1.0.1.3.dist-info/RECORD
