Metadata-Version: 2.1
Name: odoo-addon-stock_picking_report_qty_undelivered
Version: 16.0.1.0.1.3
Summary: Print a summary of the undelivered quantity
Home-page: https://github.com/OCA/stock-logistics-reporting
Author: Moduon, Odoo Community Association (OCA)
Author-email: support@odoo-community.org
License: GPL-3
Classifier: Programming Language :: Python
Classifier: Framework :: Odoo
Classifier: Framework :: Odoo :: 16.0
Classifier: License :: OSI Approved :: GNU General Public License v3 (GPLv3)
Classifier: Development Status :: 3 - Alpha
Requires-Python: >=3.10
Requires-Dist: odoo <16.1dev,>=16.0a
